README.rst
setup.cfg
setup.py
charlesbot_rundeck/__init__.py
charlesbot_rundeck/http.py
charlesbot_rundeck/rundeck.py
charlesbot_rundeck/rundeck_job.py
charlesbot_rundeck/rundeck_lock.py
charlesbot_rundeck.egg-info/PKG-INFO
charlesbot_rundeck.egg-info/SOURCES.txt
charlesbot_rundeck.egg-info/dependency_links.txt
charlesbot_rundeck.egg-info/not-zip-safe
charlesbot_rundeck.egg-info/pbr.json
charlesbot_rundeck.egg-info/requires.txt
charlesbot_rundeck.egg-info/top_level.txt