Metadata-Version: 1.1
Name: charlesbot-rundeck
Version: 0.2.0
Summary: A Charlesbot plugin that integrates with Rundeck
Home-page: https://github.com/marvinpinto/charlesbot-rundeck
Author: Marvin Pinto
Author-email: marvin@pinto.im
License: MIT
Keywords: slack robot chatops charlesbot charlesbot-rundeck
Platform: UNKNOWN
Classifier: Development Status :: 3 - Alpha
Classifier: Intended Audience :: Developers
Classifier: License :: OSI Approved :: MIT License
Classifier: Programming Language :: Python :: 3.4
